script.py
compctl-0.0.0.dist-info/METADATA
compctl-0.0.0.dist-info/WHEEL
compctl-0.0.0.dist-info/entry_points.txt
compctl-0.0.0.dist-info/top_level.txt
compctl-0.0.0.dist-info/RECORD
