Metadata-Version: 2.1
Name: compctl
Version: 0.0.0
Summary: A simple script.
Home-page: https://github.com/fridex
Author: me
Author-email: fridex.devel@gmail.com
Maintainer: me
Maintainer-email: fridex.devel@gmail.com
License: LGPLv3+
Classifier: Intended Audience :: Developers
Requires-Dist: pip >=9
